xml_cleaner/__init__.py
xml_cleaner/constants.py
xml_cleaner/quoted_expressions.py
xml_cleaner/regular_expressions.py
xml_cleaner/sentence_tokenizer.py
xml_cleaner/wiki_markup_processing.py
xml_cleaner/word_tokenizer.py
xml_cleaner-2.0.3.dist-info/DESCRIPTION.rst
xml_cleaner-2.0.3.dist-info/METADATA
xml_cleaner-2.0.3.dist-info/RECORD
xml_cleaner-2.0.3.dist-info/WHEEL
xml_cleaner-2.0.3.dist-info/metadata.json
xml_cleaner-2.0.3.dist-info/top_level.txt
